artificienlib/__init__.py
artificienlib/constants.py
artificienlib/syftfunctions.py
artificienlib-0.1.6.dist-info/METADATA
artificienlib-0.1.6.dist-info/WHEEL
artificienlib-0.1.6.dist-info/top_level.txt
artificienlib-0.1.6.dist-info/RECORD
